pydantic_configuration/__init__.py
pydantic_configuration/configuration.py
pydantic_configuration-0.1.0.dist-info/LICENSE
pydantic_configuration-0.1.0.dist-info/METADATA
pydantic_configuration-0.1.0.dist-info/WHEEL
pydantic_configuration-0.1.0.dist-info/RECORD
