Metadata-Version: 2.3
Name: pydantic-configuration
Version: 0.1.0
Summary: 
License: MIT
Keywords: pydantic,configuration,yaml,env
Author: Mirage_
Author-email: gaoxuran111@gmail.com
Requires-Python: >=3.13,<4.0
Classifier: License :: OSI Approved :: MIT License
Classifier: Programming Language :: Python :: 3
Classifier: Programming Language :: Python :: 3.13
Requires-Dist: poetry-core (>=2.0.0)
Requires-Dist: pydantic (>=2.11.9)
Requires-Dist: pydantic-settings (>=2.11.0,<3.0.0)
Project-URL: Homepage, https://github.com/gxxxr-111/pydantic-configuration
Project-URL: Repository, https://github.com/gxxxr-111/pydantic-configuration
